googleapis/__init__.py
googleapis/__init__.pyc
googleapis/codegen/__init__.py
googleapis/codegen/__init__.pyc
googleapis/codegen/api.py
googleapis/codegen/api.pyc
googleapis/codegen/api_exception.py
googleapis/codegen/api_exception.pyc
googleapis/codegen/api_exception_test.py
googleapis/codegen/api_library_generator.py
googleapis/codegen/api_library_generator.pyc
googleapis/codegen/api_test.py
googleapis/codegen/configuration_test.py
googleapis/codegen/cpp_generator.py
googleapis/codegen/cpp_generator.pyc
googleapis/codegen/cpp_generator_test.py
googleapis/codegen/cpp_import_manager.py
googleapis/codegen/cpp_import_manager.pyc
googleapis/codegen/cpp_import_manager_test.py
googleapis/codegen/csharp_generator.py
googleapis/codegen/csharp_generator.pyc
googleapis/codegen/csharp_generator_test.py
googleapis/codegen/dart_generator.py
googleapis/codegen/dart_generator.pyc
googleapis/codegen/dart_generator_test.py
googleapis/codegen/data_types.py
googleapis/codegen/data_types.pyc
googleapis/codegen/data_types_test.py
googleapis/codegen/data_value.py
googleapis/codegen/data_value_test.py
googleapis/codegen/django_helpers.py
googleapis/codegen/django_helpers.pyc
googleapis/codegen/documenting_language_model_test.py
googleapis/codegen/expand_templates.py
googleapis/codegen/generate_library.py
googleapis/codegen/generate_library_test.py
googleapis/codegen/generator.py
googleapis/codegen/generator.pyc
googleapis/codegen/generator_lookup.py
googleapis/codegen/generator_lookup.pyc
googleapis/codegen/generator_lookup_test.py
googleapis/codegen/generator_test.py
googleapis/codegen/gwt_generator.py
googleapis/codegen/gwt_generator.pyc
googleapis/codegen/gwt_generator_test.py
googleapis/codegen/import_definition.py
googleapis/codegen/import_definition.pyc
googleapis/codegen/java_generator.py
googleapis/codegen/java_generator.pyc
googleapis/codegen/java_generator_test.py
googleapis/codegen/java_import_manager.py
googleapis/codegen/java_import_manager.pyc
google_apis_client_generator-1.7.0.dist-info/LICENSE
google_apis_client_generator-1.7.0.dist-info/METADATA
google_apis_client_generator-1.7.0.dist-info/WHEEL
google_apis_client_generator-1.7.0.dist-info/entry_points.txt
google_apis_client_generator-1.7.0.dist-info/top_level.txt
google_apis_client_generator-1.7.0.dist-info/RECORD
