Metadata-Version: 2.1
Name: google-apis-client-generator
Version: 1.7.0
Summary: Google Apis Client Generator
Home-page: https://github.com/google/apis-client-generator/
Author: Google Inc.
Author-email: opensource-apis-client-generator@google.com
License: UNKNOWN
Platform: UNKNOWN
Requires-Dist: django (<2.0.0dev,>=1.11.0)
Requires-Dist: httplib2 (<2.0.0dev,>=0.9.2)
Requires-Dist: google-apputils (<2.0.0dev,>=0.4.2)
Requires-Dist: python-gflags (<4.0.0dev,>=2.0)
Requires-Dist: google-api-python-client (<2.0.0dev,>=1.0.0)
